[
  {
    "id": 27,
    "title": "خواندن دوبارهٔ بوف کور",
    "slug": "خواندن-دوباره-بوف-کور",
    "category": {
      "id": 3,
      "name": "Literature",
      "name_fa": "ادبیات",
      "slug": "literature",
      "description": "",
      "icon": "❝",
      "post_count": 1
    },
    "language": "fa",
    "excerpt": "هر بار چیز تازه‌ای از این کتاب بیرون می‌کشم.",
    "cover_image": null,
    "source_url": "",
    "created_at": "2026-05-25T00:16:42.515564+03:30",
    "body": "هر بار چیز تازه‌ای از این کتاب بیرون می‌کشم."
  },
  {
    "id": 29,
    "title": "Eruption — One Way Ticket",
    "slug": "eruption-one-way-ticket",
    "category": {
      "id": 2,
      "name": "Art",
      "name_fa": "هنر",
      "slug": "art",
      "description": "",
      "icon": "✦",
      "post_count": 1
    },
    "language": "en",
    "excerpt": "A track I've had on repeat — try the player.",
    "cover_image": null,
    "source_url": "",
    "created_at": "2026-05-22T22:16:42.515564+03:30",
    "body": "A track I've had on repeat. Hit play below — the waveform fills in as it streams."
  }
]